<DOMSymbolItem xmlns:xsi="http://www.w3.org/2001/XMLSchema-instance" xmlns="http://ns.adobe.com/xfl/2008/" name="Assets/SinkingGraphics/CylinderAssets/cylinderbase" itemID="5a284825-0000001a" lastModified="1512589349">
  <timeline>
    <DOMTimeline name="cylinderbase">
      <layers>
        <DOMLayer name="Layer_1" color="#00FFFF" current="true" isSelected="true">
          <frames>
            <DOMFrame index="0" keyMode="9728">
              <elements>
                <DOMShape selected="true" isDrawingObject="true">
                  <matrix>
                    <Matrix tx="-245.85" ty="-374.45"/>
                  </matrix>
                  <fills>
                    <FillStyle index="1">
                      <RadialGradient>
                        <matrix>
                          <Matrix a="0.061279296875" d="0.061279296875" tx="245.8" ty="375.4"/>
                        </matrix>
                        <GradientEntry color="#FFFFFF" ratio="0"/>
                        <GradientEntry color="#A3A3A3" ratio="0"/>
                        <GradientEntry color="#373737" ratio="0"/>
                        <GradientEntry color="#181818" ratio="0"/>
                        <GradientEntry ratio="1"/>
                      </RadialGradient>
                    </FillStyle>
                    <FillStyle index="2">
                      <SolidColor/>
                    </FillStyle>
                    <FillStyle index="3">
                      <RadialGradient>
                        <matrix>
                          <Matrix a="0.00537109375" d="0.00537109375" tx="290.8" ty="372.25"/>
                        </matrix>
                        <GradientEntry color="#FFFFFF" ratio="0"/>
                        <GradientEntry color="#A3A3A3" ratio="0"/>
                        <GradientEntry color="#373737" ratio="0"/>
                        <GradientEntry color="#181818" ratio="0"/>
                        <GradientEntry ratio="1"/>
                      </RadialGradient>
                    </FillStyle>
                    <FillStyle index="4">
                      <RadialGradient>
                        <matrix>
                          <Matrix a="0.00140380859375" d="0.00140380859375" tx="291.2" ty="369.95"/>
                        </matrix>
                        <GradientEntry color="#FFFFFF" ratio="0"/>
                        <GradientEntry color="#A3A3A3" ratio="0"/>
                        <GradientEntry color="#373737" ratio="0"/>
                        <GradientEntry color="#181818" ratio="0"/>
                        <GradientEntry ratio="1"/>
                      </RadialGradient>
                    </FillStyle>
                    <FillStyle index="5">
                      <RadialGradient>
                        <matrix>
                          <Matrix a="0.00579833984375" d="0.00579833984375" tx="292.25" ty="372.95"/>
                        </matrix>
                        <GradientEntry color="#FFFFFF" ratio="0"/>
                        <GradientEntry color="#A3A3A3" ratio="0"/>
                        <GradientEntry color="#373737" ratio="0"/>
                        <GradientEntry color="#181818" ratio="0"/>
                        <GradientEntry ratio="1"/>
                      </RadialGradient>
                    </FillStyle>
                    <FillStyle index="6">
                      <RadialGradient>
                        <matrix>
                          <Matrix a="0.00360107421875" d="0.00360107421875" tx="294.55" ty="374.05"/>
                        </matrix>
                        <GradientEntry color="#FFFFFF" ratio="0"/>
                        <GradientEntry color="#A3A3A3" ratio="0"/>
                        <GradientEntry color="#373737" ratio="0"/>
                        <GradientEntry color="#181818" ratio="0"/>
                        <GradientEntry ratio="1"/>
                      </RadialGradient>
                    </FillStyle>
                    <FillStyle index="7">
                      <RadialGradient>
                        <matrix>
                          <Matrix a="0.00341796875" d="0.00341796875" tx="293" ty="373.55"/>
                        </matrix>
                        <GradientEntry color="#FFFFFF" ratio="0"/>
                        <GradientEntry color="#A3A3A3" ratio="0"/>
                        <GradientEntry color="#373737" ratio="0"/>
                        <GradientEntry color="#181818" ratio="0"/>
                        <GradientEntry ratio="1"/>
                      </RadialGradient>
                    </FillStyle>
                  </fills>
                  <strokes>
                    <StrokeStyle index="1">
                      <SolidStroke scaleMode="normal" weight="0.65">
                        <fill>
                          <SolidColor/>
                        </fill>
                      </SolidStroke>
                    </StrokeStyle>
                  </strokes>
                  <edges>
                    <Edge fillStyle1="1" edges="!3986 7563[3973 7561 3963 7559!3963 7559[3959 7557 3956 7555!3956 7555[3946 7549 3938 7534!3938 7534[3919 7504 3924 7475!3924 7475[3925 7467 3929 7457!3929 7457[3933 7454 3938 7450!3938 7450[3940 7448 3941 7446!3941 7446[3952 7434 3971
 7425!3971 7425|4021 7403!4021 7403[4038 7395 4057 7387!4057 7387|4062 7385!4062 7385[4076 7378 4090 7371"/>
                    <Edge fillStyle1="2" edges="
!4090 7371[4111 7361 4132 7351!4132 7351[4133 7350 4134 7350!4134 7350[4142 7350 4145 7352!4145 7352[4150 7353 4151 7357!4151 7357[4163 7362 4182 7371"/>
                    <Edge fillStyle1="1" edges="
!4182 7371[4192 7375 4202 7381!4202 7381[4205 7382 4209 7383!4209 7383[4229 7383 4257 7386!4257 7386[4452 7409 4696 7415!4696 7415[4844 7419 5138 7417!5138 7417[5384 7415 5506 7403!5506 7403[5543 7400 5575 7394!5575 7394[5618 7384 5657
 7371!5657 7371[5658 7371 5659 7371"/>
                    <Edge fillStyle0="2" fillStyle1="1" edges="
!4090 7371|4182 7371"/>
                    <Edge fillStyle1="1" strokeStyle="1" edges="
!5878.5 7528.5[5822.75 #1D91.C2 5603 7602!5603 7602[5309 7646 4892 7646!4892 7646[4475 7646 4181 7602!4181 7602[4058 7584 3986 7563"/>
                    <Edge fillStyle1="2" edges="
!5659 7371[5663 7364 5669 7357!5669 7357[5675 7351 5682 7347!5682 7347[5681 7346 5681 7345!5681 7345[5687 7339 5694 7340!5694 7340[5698 7338 5702 7337!5702 7337[5704 7334 5708 7333!5708 7333[5714 7332 5723 7336!5723 7336[5769 7352 5813
 7371"/>
                    <Edge fillStyle0="1" fillStyle1="3" edges="
!5758 7392.5[#167F.77 #1CDF.93 5761 7391!5761 7391[5766 7391 5783 7401!5783 7401[#1698.C9 #1CEA.63 5787 7404"/>
                    <Edge fillStyle1="3" edges="
!5757 7393.5[#167D.67 #1CE0.DC 5758 7392.5"/>
                    <Edge fillStyle0="1" edges="
!5757 7393.5[#167B.5E #1CE0.24 5754 7391!5754 7391[#167C.04 #1CDF.9B 5758 7392.5"/>
                    <Edge fillStyle0="1" fillStyle1="3" edges="
!5863 7494.5|5861 7493!5861 7493[5859 7480 5841 7462!5841 7462[5825 7446 5815 7443!5815 7443[5802 7441 5797 7438!5797 7438|5785 7428!5785 7428[5758 7415 5751 7403!5751 7403[#1678.7 #1CE4.88 5757 7393.5"/>
                    <Edge fillStyle0="3" fillStyle1="5" edges="
!5830 7433.5[#16B7.78 #1D01.DE 5800 7422!5800 7422[5783 7418 5780 7410!5780 7410|5787 7404"/>
                    <Edge fillStyle0="1" fillStyle1="5" edges="
!5787 7404|5791 7400!5791 7400|5810.5 7405"/>
                    <Edge fillStyle0="1" fillStyle1="4" edges="
!5810.5 7405|5811 7389!5811 7389[5814 7383 5821 7383!5821 7383|5821 7380!5821 7380|5833 7384!5833 7384[5836 7386 5838 7391!5838 7391|5830 7407!5830 7407|5829 7409.5"/>
                    <Edge fillStyle0="4" fillStyle1="5" edges="
!5810.5 7405|5827 7409!5827 7409[#16C4.08 #1CF1.35 5829 7409.5"/>
                    <Edge fillStyle0="1" fillStyle1="5" edges="
!5829 7409.5[#16CD.B9 #1CF3.6A 5844 7415!5844 7415[#16DA.75 #1CFA.B1 5862 7430"/>
                    <Edge fillStyle0="1" edges="
!5910 7456[#1716.E6 7451.5 5907 7445!5907 7445[5903 7440 5899 7435!5899 7435[5890 7418 5884 7410!5884 7410[5870 7396 5838 7382!5838 7382[5826 7376 5813 7371"/>
                    <Edge fillStyle0="1" fillStyle1="6" edges="
!5871.5 7436.5[#16F2.07 7433 5881 7433!5881 7433|5880 7431!5880 7431[5900 7433 5907 7446!5907 7446[#1715.29 #1D19.C7 5910 7456"/>
                    <Edge fillStyle0="7" fillStyle1="6" edges="
!5871.5 7519.5[#16F1.BB #1D5E.D9 5875 7518!5875 7518[5878 7516 5880 7507!5880 7507[5885 7498 5887 7494!5887 7494[#1701.8A #1D41.8F 5889.5 7486!5889.5 7486|5889.5 7485.5"/>
                    <Edge fillStyle0="5" fillStyle1="7" edges="
!5830 7433.5[#16C6.3F #1D04.D1 5834 7426!5834 7426[5838 7422 5842 7423!5842 7423[5845 7424 5852 7433!5852 7433[5854 7435 5864 7442!5864 7442[5871 7447 5874 7452!5874 7452[5879 7459 5883 7473!5883 7473|5889 7482!5889 7482[#1701.A4 #1D3B.99
 5889.5 7485.5"/>
                    <Edge fillStyle0="5" fillStyle1="6" edges="
!5889.5 7485.5[5891 #1D38.6 5891 7473!5891 7473[5890 7458 5891 7453!5891 7453[5874 7451 5871 7441!5871 7441[5871 #1D0E.D 5871.5 7437"/>
                    <Edge fillStyle1="6" edges="
!5910 7456[5911 #1D25.18 5911 7468!5911 7468[5911 #1D37.FE 5910 7488.5"/>
                    <Edge fillStyle0="5" fillStyle1="6" edges="
!5910 7488.5[#1714.EA #1D48.37 5907 7501!5907 7501|5902 7512.5"/>
                    <Edge fillStyle1="5" edges="
!5910 7488.5[#1717.C9 #1D49.5 5909 7504!5909 7504[#1713.12 #1D55.25 5902 7512.5"/>
                    <Edge fillStyle1="6" edges="
!5902 7512.5|5899 7519!5899 7519[5897 7528 5895 7529!5895 7529[5891 7532 5886 7530!5886 7530[#16F9.82 #1D69.67 5878.5 7528.5"/>
                    <Edge fillStyle0="1" fillStyle1="6" edges="
!5878.5 7528.5[5871 #1D65.9B 5871 7520!5871 7520|5871.5 7519.5"/>
                    <Edge fillStyle0="1" edges="
!5862 7430[#16E6.A4 #1D05.15 5863 7428!5863 7428[#16EB.58 #1D08.58 5871.5 7436.5"/>
                    <Edge fillStyle1="5" edges="
!5862 7430[#16E6.FE #1D06.FE 5864 7432!5864 7432[#16EB.18 #1D0A.52 5871.5 7437"/>
                    <Edge fillStyle1="6" edges="
!5871.5 7437|5871.5 7436.5"/>
                    <Edge fillStyle0="3" fillStyle1="7" edges="
!5863 7494.5[5865 #1D43.E4 5865 7489!5865 7489|5863 7483!5863 7483[5858 7474 5861 7465!5861 7465[5848 7461 5837 7450!5837 7450[5829 7442 5830 7434!5830 7434|5830 7433.5"/>
                    <Edge fillStyle0="1" fillStyle1="7" edges="
!5871.5 7519.5[#16ED.09 7520 5865 7520!5865 7520|5855 7520!5855 7520|5846 7518!5846 7518[5841 7515 5841 7511!5841 7511[5842 7504 5854 7500!5854 7500[#16E4.74 #1D49.A7 5863 7494.5"/>
                    <Edge fillStyle0="2" fillStyle1="1" edges="
!5659 7371|5813 7371"/>
                    <Edge cubics="!4181 7602(;4103,7590 4040,7578 3986,7563q4181 7602Q4058 7584q3986 7563);"/>
                    <Edge cubics="!5603 7602(;5407,7631 5170,7646 4892,7646q5603 7602Q5309 7646q4892 7646);"/>
                    <Edge cubics="!4892 7646(;4615,7646 4377,7631 4181,7602q4892 7646Q4475 7646q4181 7602);"/>
                    <Edge cubics="!4257 7386(;4549,7420 4844,7419 5138,7417q4257 7386Q4452 7409q4696 7415Q4844 7419q5138 7417);"/>
                    <Edge cubics="!5138 7417(;5261,7416 5384,7415 5506,7403q5138 7417Q5384 7415q5506 7403);"/>
                    <Edge cubics="!5506 7403(;5530,7401 5553,7399 5575,7394q5506 7403 5575 7394);"/>
                    <Edge cubics="!5659 7371(;5662,7366 5664,7362 5669,7357q5659 7371Q5663 7364q5669 7357);"/>
                    <Edge cubics="!5708 7333(;5714,7332 5718,7334 5723,7336q5708 7333Q5714 7332q5723 7336);"/>
                    <Edge cubics="!5838 7382(;5854,7389 5871,7397 5884,7410q5838 7382Q5870 7396q5884 7410);"/>
                    <Edge cubics="!3941 7446(;3949,7437 3960,7430 3971,7425q3941 7446Q3952 7434q3971 7425);"/>
                    <Edge cubics="!4134 7350(;4138,7350 4142,7350 4145,7352q4134 7350Q4142 7350q4145 7352);"/>
                    <Edge cubics="!3924 7475(;3920,7496 3928,7517 3938,7534q3924 7475Q3919 7504q3938 7534);"/>
                    <Edge cubics="!3938 7534(;3943,7542 3949,7551 3956,7555q3938 7534Q3946 7549q3956 7555);"/>
                    <Edge cubics="!4132 7351(;4133,7350 4133,7350 4134,7350q4132 7351Q4133 7350q4134 7350);"/>
                    <Edge cubics="!4202 7381(;4204,7382 4206,7382 4209,7383q4202 7381Q4205 7382q4209 7383);"/>
                    <Edge cubics="!4209 7383(;4222,7383 4238,7384 4257,7386q4209 7383Q4229 7383q4257 7386);"/>
                    <Edge cubics="!4145 7352(;4148,7353 4150,7355 4151,7357q4145 7352Q4150 7353q4151 7357);"/>
                    <Edge cubics="!3929 7457(;3932,7454 3935,7453 3938,7450q3929 7457Q3933 7454q3938 7450);"/>
                    <Edge cubics="!3938 7450(;3939,7449 3940,7447 3941,7446q3938 7450Q3940 7448q3941 7446);"/>
                    <Edge cubics="!4057 7387(;4057,7387 4062,7385 4062,7385q4057 7387 4062 7385);"/>
                    <Edge cubics="!4021 7403(;4033,7398 4044,7393 4057,7387q4021 7403Q4038 7395q4057 7387);"/>
                    <Edge cubics="!3971 7425(;3971,7425 4021,7403 4021,7403q3971 7425 4021 7403);"/>
                    <Edge cubics="!3956 7555(;3958,7556 3960,7558 3963,7559q3956 7555Q3959 7557q3963 7559);"/>
                    <Edge cubics="!3986 7563(;3978,7562 3970,7560 3963,7559q3986 7563Q3973 7561q3963 7559);"/>
                    <Edge cubics="!3929 7457(;3927,7463 3925,7470 3924,7475q3929 7457Q3925 7467q3924 7475);"/>
                    <Edge cubics="!5899 7435(;5901,7438 5904,7442 5907,7445q5899 7435Q5903 7440q5907 7445);"/>
                    <Edge cubics="!5884 7410(;5888,7415 5892,7423 5899,7435q5884 7410Q5890 7418q5899 7435);"/>
                    <Edge cubics="!5682 7347(;5681,7346 5681,7346 5681,7345q5682 7347Q5681 7346q5681 7345);"/>
                    <Edge cubics="!5702 7337(;5703,7335 5706,7334 5708,7333q5702 7337Q5704 7334q5708 7333);"/>
                    <Edge cubics="!5694 7340(;5697,7339 5699,7338 5702,7337q5694 7340Q5698 7338q5702 7337);"/>
                    <Edge cubics="!5681 7345(;5685,7340 5690,7339 5694,7340q5681 7345Q5687 7339q5694 7340);"/>
                    <Edge cubics="!5669 7357(;5673,7353 5678,7349 5682,7347q5669 7357Q5675 7351q5682 7347);"/>
                    <Edge cubics="!4182 7371(;4188,7374 4195,7377 4202,7381q4182 7371Q4192 7375q4202 7381);"/>
                    <Edge cubics="!4090 7371(;4090,7371 4182,7371 4182,7371q4090 7371 4182 7371);"/>
                    <Edge cubics="!4151 7357(;4159,7360 4169,7365 4182,7371q4151 7357Q4163 7362q4182 7371);"/>
                    <Edge cubics="!4090 7371(;4104,7365 4118,7357 4132,7351q4090 7371Q4111 7361q4132 7351);"/>
                    <Edge cubics="!4062 7385(;4071,7381 4080,7375 4090,7371q4062 7385Q4076 7378q4090 7371);"/>
                    <Edge cubics="!5813 7371(;5822,7375 5830,7378 5838,7382q5813 7371Q5826 7376q5838 7382);"/>
                    <Edge cubics="!5723 7336(;5754,7347 5784,7358 5813,7371q5723 7336Q5769 7352q5813 7371);"/>
                    <Edge cubics="!5657 7371(;5658,7371 5658,7371 5659,7371q5657 7371Q5658 7371q5659 7371);"/>
                    <Edge cubics="!5575 7394(;5603,7387 5631,7379 5657,7371q5575 7394Q5618 7384q5657 7371);"/>
                    <Edge cubics="!5659 7371(;5659,7371 5813,7371 5813,7371q5659 7371 5813 7371);"/>
                    <Edge cubics="!5841 7462(;5833,7454 5825,7446 5815,7443q5841 7462Q5825 7446q5815 7443);"/>
                    <Edge cubics="!5815 7443(;5809,7441 5802,7441 5797,7438q5815 7443Q5802 7441q5797 7438);"/>
                    <Edge cubics="!5797 7438(;5792,7435 5789,7431 5785,7428q5797 7438 5785 7428);"/>
                    <Edge cubics="!5785 7428(;5774,7419 5758,7415 5751,7403q5785 7428Q5758 7415q5751 7403);"/>
                    <Edge cubics="!5761 7391(;5769,7391 5776,7397 5783,7401q5761 7391Q5766 7391q5783 7401);"/>
                    <Edge cubics="!5861 7493(;5859,7481 5850,7471 5841,7462q5861 7493Q5859 7480q5841 7462);"/>
                    <Edge cubics="!5833 7384(;5835,7385 5837,7388 5838,7391q5833 7384Q5836 7386q5838 7391);"/>
                    <Edge cubics="!5838 7391(;5835,7396 5832,7401 5830,7407q5838 7391 5830 7407);"/>
                    <Edge cubics="!5811 7389(;5813,7385 5817,7383 5821,7383q5811 7389Q5814 7383q5821 7383);"/>
                    <Edge cubics="!5821 7383(;5821,7382 5821,7381 5821,7380q5821 7383 5821 7380);"/>
                    <Edge cubics="!5821 7380(;5825,7382 5829,7382 5833,7384q5821 7380 5833 7384);"/>
                    <Edge cubics="!5800 7422(;5792,7420 5783,7418 5780,7410q5800 7422Q5783 7418q5780 7410);"/>
                    <Edge cubics="!5899 7519(;5898,7523 5898,7527 5895,7529q5899 7519Q5897 7528q5895 7529);"/>
                    <Edge cubics="!5895 7529(;5892,7531 5889,7531 5886,7530q5895 7529Q5891 7532q5886 7530);"/>
                    <Edge cubics="!5891 7453(;5882,7452 5873,7448 5871,7441q5891 7453Q5874 7451q5871 7441);"/>
                    <Edge cubics="!5881 7433(;5881,7432 5880,7432 5880,7431q5881 7433 5880 7431);"/>
                    <Edge cubics="!5880 7431(;5891,7432 5902,7437 5907,7446q5880 7431Q5900 7433q5907 7446);"/>
                    <Edge cubics="!5842 7423(;5846,7424 5849,7429 5852,7433q5842 7423Q5845 7424q5852 7433);"/>
                    <Edge cubics="!5852 7433(;5859,7440 5869,7444 5874,7452q5852 7433Q5854 7435q5864 7442Q5871 7447q5874 7452);"/>
                    <Edge cubics="!5874 7452(;5879,7459 5879,7467 5883,7473q5874 7452Q5879 7459q5883 7473);"/>
                    <Edge cubics="!5883 7473(;5885,7476 5888,7478 5889,7482q5883 7473Q5889 7482q5889 7482);"/>
                    <Edge cubics="!5880 7507(;5879,7511 5878,7516 5875,7518q5880 7507Q5878 7516q5875 7518);"/>
                    <Edge cubics="!5865 7520(;5862,7520 5859,7520 5855,7520q5865 7520 5855 7520);"/>
                    <Edge cubics="!5855 7520(;5852,7519 5849,7519 5846,7518q5855 7520 5846 7518);"/>
                    <Edge cubics="!5846 7518(;5843,7516 5841,7514 5841,7511q5846 7518Q5841 7515q5841 7511);"/>
                    <Edge cubics="!5841 7511(;5842,7505 5848,7502 5854,7500q5841 7511Q5842 7504q5854 7500);"/>
                    <Edge cubics="!5865 7489(;5865,7487 5863,7485 5863,7483q5865 7489 5863 7483);"/>
                    <Edge cubics="!5863 7483(;5860,7478 5859,7471 5861,7465q5863 7483Q5858 7474q5861 7465);"/>
                    <Edge cubics="!5861 7465(;5852,7462 5844,7457 5837,7450q5861 7465Q5848 7461q5837 7450);"/>
                    <Edge cubics="!5837 7450(;5833,7446 5829,7440 5830,7434q5837 7450Q5829 7442q5830 7434);"/>
                    <Edge cubics="!5830 7434(;5830,7428 5836,7422 5842,7423q5830 7434Q5830 7429q5834 7426Q5838 7422q5842 7423);"/>
                    <Edge cubics="!5757 7394(;5757,7393 5757,7393 5758,7393q5757 7394Q5757 7393q5758 7393);"/>
                    <Edge cubics="!5751 7403(;5752,7399 5754,7396 5757,7394q5751 7403Q5752 7397q5757 7394);"/>
                    <Edge cubics="!5757 7394(;5756,7393 5755,7392 5754,7391q5757 7394Q5755 7392q5754 7391);"/>
                    <Edge cubics="!5754 7391(;5755,7392 5757,7392 5758,7393q5754 7391Q5756 7392q5758 7393);"/>
                    <Edge cubics="!5758 7393(;5759,7392 5760,7392 5761,7391q5758 7393Q5759 7392q5761 7391);"/>
                    <Edge cubics="!5787 7404(;5787,7404 5791,7400 5791,7400q5787 7404 5791 7400);"/>
                    <Edge cubics="!5780 7410(;5780,7410 5787,7404 5787,7404q5780 7410 5787 7404);"/>
                    <Edge cubics="!5783 7401(;5784,7402 5786,7403 5787,7404q5783 7401Q5785 7402q5787 7404);"/>
                    <Edge cubics="!5811 7405(;5811,7405 5811,7389 5811,7389q5811 7405 5811 7389);"/>
                    <Edge cubics="!5791 7400(;5791,7400 5811,7405 5811,7405q5791 7400 5811 7405);"/>
                    <Edge cubics="!5830 7407(;5830,7407 5829,7410 5829,7410q5830 7407 5829 7410);"/>
                    <Edge cubics="!5827 7409(;5828,7409 5828,7409 5829,7410q5827 7409Q5828 7409q5829 7410);"/>
                    <Edge cubics="!5829 7410(;5835,7411 5840,7412 5844,7415q5829 7410Q5838 7411q5844 7415);"/>
                    <Edge cubics="!5811 7405(;5811,7405 5827,7409 5827,7409q5811 7405 5827 7409);"/>
                    <Edge cubics="!5889 7482(;5890,7483 5890,7485 5890,7486q5889 7482Q5890 7484q5890 7486);"/>
                    <Edge cubics="!5890 7486(;5891,7482 5891,7478 5891,7473q5890 7486Q5891 7480q5891 7473);"/>
                    <Edge cubics="!5910 7456(;5911,7459 5911,7463 5911,7468q5910 7456Q5911 7461q5911 7468);"/>
                    <Edge cubics="!5891 7473(;5890,7463 5890,7456 5891,7453q5891 7473Q5890 7458q5891 7453);"/>
                    <Edge cubics="!5910 7456(;5911,7453 5910,7450 5907,7445q5910 7456Q5911 7452q5907 7445);"/>
                    <Edge cubics="!5907 7446(;5908,7449 5909,7452 5910,7456q5907 7446Q5909 7450q5910 7456);"/>
                    <Edge cubics="!5910 7489(;5909,7494 5908,7498 5907,7501q5910 7489Q5909 7496q5907 7501);"/>
                    <Edge cubics="!5910 7489(;5911,7494 5911,7499 5909,7504q5910 7489Q5912 7497q5909 7504);"/>
                    <Edge cubics="!5907 7501(;5907,7501 5902,7513 5902,7513q5907 7501 5902 7513);"/>
                    <Edge cubics="!5909 7504(;5908,7507 5905,7510 5902,7513q5909 7504Q5907 7509q5902 7513);"/>
                    <Edge cubics="!5887 7494(;5886,7497 5883,7501 5880,7507q5887 7494Q5885 7498q5880 7507);"/>
                    <Edge cubics="!5886 7530(;5883,7529 5881,7529 5879,7529q5886 7530Q5882 7529q5879 7529);"/>
                    <Edge cubics="!5902 7513(;5902,7513 5899,7519 5899,7519q5902 7513 5899 7519);"/>
                    <Edge cubics="!5911 7468(;5911,7476 5911,7483 5910,7489q5911 7468Q5911 7480q5910 7489);"/>
                    <Edge cubics="!5890 7486(;5890,7489 5889,7491 5887,7494q5890 7486Q5890 7490q5887 7494);"/>
                    <Edge cubics="!5862 7430(;5863,7429 5863,7429 5863,7428q5862 7430Q5863 7429q5863 7428);"/>
                    <Edge cubics="!5862 7430(;5863,7431 5863,7431 5864,7432q5862 7430Q5863 7431q5864 7432);"/>
                    <Edge cubics="!5864 7432(;5866,7433 5869,7435 5872,7437q5864 7432Q5867 7434q5872 7437);"/>
                    <Edge cubics="!5871 7441(;5871,7440 5871,7438 5872,7437q5871 7441Q5871 7439q5872 7437);"/>
                    <Edge cubics="!5863 7428(;5866,7431 5869,7434 5872,7437q5863 7428Q5867 7432q5872 7437);"/>
                    <Edge cubics="!5863 7495(;5863,7495 5861,7493 5861,7493q5863 7495 5861 7493);"/>
                    <Edge cubics="!5854 7500(;5858,7499 5861,7497 5863,7495q5854 7500Q5860 7498q5863 7495);"/>
                    <Edge cubics="!5863 7495(;5864,7493 5865,7491 5865,7489q5863 7495Q5865 7492q5865 7489);"/>
                    <Edge cubics="!5872 7520(;5870,7520 5868,7520 5865,7520q5872 7520Q5869 7520q5865 7520);"/>
                    <Edge cubics="!5871 7520(;5871,7520 5872,7520 5872,7520q5871 7520 5872 7520);"/>
                    <Edge cubics="!5872 7437(;5873,7434 5876,7433 5881,7433q5872 7437Q5874 7433q5881 7433);"/>
                    <Edge cubics="!5879 7529(;5874,7527 5871,7524 5871,7520q5879 7529Q5871 7526q5871 7520);"/>
                    <Edge cubics="!5875 7518(;5874,7519 5873,7519 5872,7520q5875 7518Q5874 7519q5872 7520);"/>
                    <Edge cubics="!5844 7415(;5848,7418 5854,7423 5862,7430q5844 7415Q5850 7419q5862 7430);"/>
                    <Edge cubics="!5830 7434(;5820,7429 5810,7425 5800,7422q5830 7434Q5815 7426q5800 7422);"/>
                    <Edge cubics="!5879 7529(;5842,7556 5750,7581 5603,7602q5879 7529Q5823 7570q5603 7602);"/>
                  </edges>
                </DOMShape>
              </elements>
            </DOMFrame>
          </frames>
        </DOMLayer>
      </layers>
    </DOMTimeline>
  </timeline>
</DOMSymbolItem>